xpose_gen
