Metadata-Version: 1.1
Name: xpose-generator
Version: 0.3.5
Summary: this packages creates a website based on the IR presentations at ESIPE
Home-page: https://github.com/paulollivier/xpose-generator
Author: Paul Ollivier
Author-email: contact@paulollivier.fr
License: MIT
Platform: UNKNOWN
Classifier: Development Status :: 4 - Beta
Classifier: Environment :: Console
Classifier: Intended Audience :: Developers
Classifier: Intended Audience :: Education
Classifier: License :: OSI Approved :: MIT License
Classifier: Programming Language :: Python :: 2.6
Classifier: Programming Language :: Python :: 2.7
Classifier: Programming Language :: Python :: 3
Classifier: Programming Language :: Python :: 3.4
